Metadata-Version: 1.0
Name: normbinom
Version: 0.1
Summary: Gaussian & Binomial distributions
Home-page: UNKNOWN
Author: Sukanto Mukherjee
Author-email: readrunner@protonmail.com
License: UNKNOWN
Platform: UNKNOWN
